horcruxes/__init__.py
horcruxes/crux.py
horcruxes/cruxcreator.py
horcruxes/cruxio.py
horcruxes/cruxreverser.py
horcruxes/shamir.py
horcruxes-2.7.post2.dist-info/LICENSE
horcruxes-2.7.post2.dist-info/METADATA
horcruxes-2.7.post2.dist-info/WHEEL
horcruxes-2.7.post2.dist-info/entry_points.txt
horcruxes-2.7.post2.dist-info/top_level.txt
horcruxes-2.7.post2.dist-info/RECORD
