Metadata-Version: 2.1
Name: horcruxes
Version: 2.7.post2
Summary: A command line tool to split a file into horcruxes, so that the original can be recreated with at least k horcruxes
Home-page: https://github.com/X-yl/horcruxes
Author: X-yl
License: GNU GPLv3
Platform: UNKNOWN
Requires-Python: >=3.8
Requires-Dist: click (>=7.1.2)
Requires-Dist: mmh3 (>=2.5.1)
Requires-Dist: pycryptodome (>=3.9.8)
Requires-Dist: tqdm (>=4.48.2)
